{
    "labels": {
        "algorithm name": "pacsynth",
        "target dataset": "national2019",
        "epsilon": "10",
        "variant label": "preprocessor-epsilon: 3",
        "algorithm type": "query matching",
        "library name": "smartnoise-synth",
        "feature set name": "family-focused",
        "privacy category": "dp",
        "deid data id": "44e2092e155fe2b9b97c2286bc404ed42a8f0cd8",
        "features list": "PUMA, AGEP, SEX, MSP, HISP, RAC1P, NOC, NPF, OWN_RENT, PINCP_DECILE, POVPIP",
        "privacy label detail": "The pac-synth synthesizer will suppress marginal combinations that could uniquely fingerprint individuals (similar to k-anonymity). pac-synth is a differentially-private synthesizer that computes differentially private marginals to build synthetic data.   ",
        "submission timestamp": "5/20/2023 00:00:00",
        "team": "CRC",
        "research papers": "https://github.com/microsoft/synthetic-data-showcase/tree/main/docs/dp"
    }
}