{
    "labels": {
        "team": "CCAIM",
        "submission timestamp": "3/9/2023 3:33:23",
        "target dataset": "national2019",
        "algorithm name": "adsgan",
        "variant label": "default, lambda=10",
        "submission number": 1,
        "algorithm type": "neural net",
        "library name": "synthcity",
        "feature set name": "all-features",
        "privacy category": "non_dp",
        "deid data id": "87d9498e671770dae31c84db1705c893846ea3c5",
        "features list": "PUMA, AGEP, SEX, MSP, HISP, RAC1P, NOC, NPF, HOUSING_TYPE, OWN_RENT, DENSITY, INDP, INDP_CAT, EDU, PINCP, PINCP_DECILE, POVPIP, DVET, DREM, DPHY, DEYE, DEAR, WGTP, PWGTP",
        "privacy label detail": "GDPR",
        "research papers": "https://doi.org/10.1109/jbhi.2020.2980262"
    }
}