{
    "data_description": {
        "target": {
            "filename": "tx2019",
            "records": 9276,
            "features": 24
        },
        "deid": {
            "filename": "patectgan_e_10_family_focused_tx2019",
            "records": 9276,
            "features": 11,
            "labels": {
                "algorithm name": "patectgan",
                "target dataset": "tx2019",
                "epsilon": "10",
                "variant label": "preprocessor-epsilon: 3",
                "algorithm type": "neural net",
                "library name": "smartnoise-synth",
                "feature set name": "family-focused",
                "privacy category": "dp",
                "deid data id": "34f077eec0ce71557336f9a50eeeeab1caf8b120",
                "features list": "PUMA, AGEP, SEX, MSP, HISP, RAC1P, NOC, NPF, OWN_RENT, PINCP_DECILE, POVPIP",
                "privacy label detail": "Conditional tabular GAN using Private Aggregation of Teacher Ensembles. From \u201cPATE-GAN: Generating Synthetic Data with Differential Privacy Guarantees\u201d and \u201cModeling Tabular data using Conditional GAN\u201d.",
                "submission timestamp": "5/20/2023 00:00:00",
                "team": "CRC",
                "research papers": "https://openreview.net/forum?id=S1zk9iRqF7"
            },
            "validations": {
                "values_out_of_bound": {}
            }
        },
        "features": [
            {
                "Feature Name": "PUMA",
                "Feature Description": "Public use microdata area code",
                "Feature Type": "object of type string",
                "Feature Has 'N' (N/A) values?": false
            },
            {
                "Feature Name": "AGEP",
                "Feature Description": "Person's age",
                "Feature Type": "int64",
                "Feature Has 'N' (N/A) values?": false
            },
            {
                "Feature Name": "SEX",
                "Feature Description": "Person's gender",
                "Feature Type": "int64",
                "Feature Has 'N' (N/A) values?": false
            },
            {
                "Feature Name": "MSP",
                "Feature Description": "Marital Status",
                "Feature Type": "object of type string",
                "Feature Has 'N' (N/A) values?": true
            },
            {
                "Feature Name": "HISP",
                "Feature Description": "Hispanic origin",
                "Feature Type": "int64",
                "Feature Has 'N' (N/A) values?": false
            },
            {
                "Feature Name": "RAC1P",
                "Feature Description": "Person's Race",
                "Feature Type": "int64",
                "Feature Has 'N' (N/A) values?": false
            },
            {
                "Feature Name": "NOC",
                "Feature Description": "Number of own children in household (unweighted)",
                "Feature Type": "object of type string",
                "Feature Has 'N' (N/A) values?": true
            },
            {
                "Feature Name": "NPF",
                "Feature Description": "Number of persons in family (unweighted)",
                "Feature Type": "object of type string",
                "Feature Has 'N' (N/A) values?": true
            },
            {
                "Feature Name": "OWN_RENT",
                "Feature Description": "Housing unit rented or owned",
                "Feature Type": "int64",
                "Feature Has 'N' (N/A) values?": false
            },
            {
                "Feature Name": "PINCP_DECILE",
                "Feature Description": "Person's total income rank (with respect to their state) discretized into 10% bins.",
                "Feature Type": "object of type string",
                "Feature Has 'N' (N/A) values?": true
            },
            {
                "Feature Name": "POVPIP",
                "Feature Description": "Income-to-poverty ratio (ex: 250 = 2.5 x poverty line)",
                "Feature Type": "object of type string",
                "Feature Has 'N' (N/A) values?": true
            }
        ]
    },
    "Univariate": {
        "divergence": "univariate/divergence.csv",
        "counts": {
            "AGEP": {
                "counts": "univariate/AGEP_counts.csv",
                "plot": "univariate/AGEP.jpg"
            },
            "PINCP_DECILE": {
                "counts": "univariate/PINCP_DECILE_counts.csv",
                "plot": "univariate/PINCP_DECILE.jpg"
            },
            "NPF": {
                "counts": "univariate/NPF_counts.csv",
                "plot": "univariate/NPF.jpg"
            },
            "MSP": {
                "counts": "univariate/MSP_counts.csv",
                "plot": "univariate/MSP.jpg"
            },
            "NOC": {
                "counts": "univariate/NOC_counts.csv",
                "plot": "univariate/NOC.jpg"
            },
            "PUMA": {
                "counts": "univariate/PUMA_counts.csv",
                "plot": "univariate/PUMA.jpg"
            },
            "POVPIP": {
                "counts": "univariate/POVPIP_counts.csv",
                "plot": "univariate/POVPIP.jpg"
            },
            "OWN_RENT": {
                "counts": "univariate/OWN_RENT_counts.csv",
                "plot": "univariate/OWN_RENT.jpg"
            },
            "RAC1P": {
                "counts": "univariate/RAC1P_counts.csv",
                "plot": "univariate/RAC1P.jpg"
            },
            "HISP": {
                "counts": "univariate/HISP_counts.csv",
                "plot": "univariate/HISP.jpg"
            },
            "SEX": {
                "counts": "univariate/SEX_counts.csv",
                "plot": "univariate/SEX.jpg"
            }
        }
    },
    "Correlations": {
        "kendall correlation difference": {
            "correlation_difference": "correlation_difference/correlation_difference.csv",
            "plot": "correlation_difference/corr_diff.jpg"
        },
        "pearson correlation difference": {
            "correlation_difference": "pearson_correlation/correlation_difference.csv",
            "plot": "pearson_correlation/pearson_corr_diff.jpg"
        }
    },
    "k_marginal": {
        "k_marginal_synopsys": {
            "subsample_error_comparison": "k_marginal_synopsys/subsample_error_comparison.csv",
            "sub_sampling_equivalent": 5,
            "k_marginal_score": 775,
            "score_in_each_puma": "k_marginal_synopsys/score_in_each_puma.csv"
        }
    },
    "worst_PUMA_breakdown": {
        "worst_2_puma_univariate": {
            "divergence": "k_marginal_breakdown/univariate/divergence.csv",
            "counts": {
                "AGEP": {
                    "counts": "k_marginal_breakdown/univariate/AGEP_counts.csv",
                    "plot": "k_marginal_breakdown/univariate/AGEP.jpg"
                },
                "PINCP_DECILE": {
                    "counts": "k_marginal_breakdown/univariate/PINCP_DECILE_counts.csv",
                    "plot": "k_marginal_breakdown/univariate/PINCP_DECILE.jpg"
                },
                "NPF": {
                    "counts": "k_marginal_breakdown/univariate/NPF_counts.csv",
                    "plot": "k_marginal_breakdown/univariate/NPF.jpg"
                },
                "MSP": {
                    "counts": "k_marginal_breakdown/univariate/MSP_counts.csv",
                    "plot": "k_marginal_breakdown/univariate/MSP.jpg"
                },
                "POVPIP": {
                    "counts": "k_marginal_breakdown/univariate/POVPIP_counts.csv",
                    "plot": "k_marginal_breakdown/univariate/POVPIP.jpg"
                },
                "NOC": {
                    "counts": "k_marginal_breakdown/univariate/NOC_counts.csv",
                    "plot": "k_marginal_breakdown/univariate/NOC.jpg"
                },
                "RAC1P": {
                    "counts": "k_marginal_breakdown/univariate/RAC1P_counts.csv",
                    "plot": "k_marginal_breakdown/univariate/RAC1P.jpg"
                },
                "PUMA": {
                    "counts": "k_marginal_breakdown/univariate/PUMA_counts.csv",
                    "plot": "k_marginal_breakdown/univariate/PUMA.jpg"
                },
                "OWN_RENT": {
                    "counts": "k_marginal_breakdown/univariate/OWN_RENT_counts.csv",
                    "plot": "k_marginal_breakdown/univariate/OWN_RENT.jpg"
                },
                "SEX": {
                    "counts": "k_marginal_breakdown/univariate/SEX_counts.csv",
                    "plot": "k_marginal_breakdown/univariate/SEX.jpg"
                },
                "HISP": {
                    "counts": "k_marginal_breakdown/univariate/HISP_counts.csv",
                    "plot": "k_marginal_breakdown/univariate/HISP.jpg"
                }
            }
        },
        "worst_2_puma_k_marginal_scores": "k_marginal_breakdown/worst_2_puma_k_marginal_scores.csv",
        "correlation_difference": {
            "pearson_correlation_difference": {
                "correlation_difference": "k_marginal_breakdown/pearson_correlation/correlation_difference.csv",
                "plot": "k_marginal_breakdown/pearson_correlation/pearson_corr_diff.jpg"
            }
        }
    },
    "propensity mean square error": {
        "pmse_score": 0.07233079834678012,
        "propensity_distribution": "propensity/propensity_distribution.csv",
        "plot": "propensity/propensity_distribution.jpg"
    },
    "pca": {
        "components_eigenvector": "pca/components_eigenvector.csv",
        "target_all_components_plot": "pca/target.png",
        "deidentified_all_components_plot": "pca/deidentified.png",
        "highlighted_plots": {
            "MSP-MSP_N-Children (AGEP < 15)": [
                "pca/target_highlighted_MSP/MSP_N.png",
                "pca/deidentified_highlighted_MSP/MSP_N.png"
            ]
        }
    },
    "inconsistencies": {
        "age": {
            "title": "Age-Based Inconsistencies",
            "description": "These inconsistencies deal with the AGE feature; records with age-based inconsistencies might have children who are married, or infants with high school diplomas",
            "inconsistencies": [
                {
                    "inconsistency_name": "child_MSP",
                    "inconsistency_description": "Children (< 15) can't be married",
                    "inconsistency_features": [
                        "AGEP",
                        "MSP"
                    ],
                    "inconsistency_violations": 503,
                    "inconsistent_data_indexes": [
                        8,
                        9,
                        32,
                        59,
                        101,
                        122,
                        144,
                        210,
                        218,
                        230,
                        232,
                        257,
                        262,
                        272,
                        281,
                        333,
                        337,
                        348,
                        349,
                        351,
                        366,
                        397,
                        398,
                        420,
                        447,
                        448,
                        494,
                        534,
                        557,
                        570,
                        592,
                        599,
                        614,
                        627,
                        634,
                        656,
                        725,
                        741,
                        760,
                        764,
                        776,
                        785,
                        797,
                        808,
                        811,
                        832,
                        835,
                        839,
                        849,
                        862,
                        888,
                        928,
                        936,
                        941,
                        950,
                        971,
                        978,
                        999,
                        1041,
                        1054,
                        1063,
                        1065,
                        1094,
                        1098,
                        1099,
                        1142,
                        1143,
                        1164,
                        1190,
                        1216,
                        1223,
                        1225,
                        1242,
                        1253,
                        1267,
                        1298,
                        1302,
                        1308,
                        1345,
                        1347,
                        1373,
                        1380,
                        1388,
                        1406,
                        1408,
                        1424,
                        1467,
                        1486,
                        1512,
                        1569,
                        1595,
                        1606,
                        1624,
                        1626,
                        1664,
                        1691,
                        1702,
                        1708,
                        1712,
                        1735,
                        1738,
                        1767,
                        1784,
                        1805,
                        1831,
                        1860,
                        1869,
                        1876,
                        1887,
                        1894,
                        1912,
                        1914,
                        1924,
                        1931,
                        2002,
                        2027,
                        2071,
                        2077,
                        2119,
                        2149,
                        2152,
                        2160,
                        2179,
                        2187,
                        2246,
                        2255,
                        2257,
                        2258,
                        2264,
                        2278,
                        2341,
                        2350,
                        2357,
                        2362,
                        2367,
                        2382,
                        2425,
                        2503,
                        2505,
                        2507,
                        2530,
                        2546,
                        2565,
                        2568,
                        2577,
                        2630,
                        2633,
                        2652,
                        2653,
                        2668,
                        2693,
                        2704,
                        2733,
                        2755,
                        2798,
                        2806,
                        2812,
                        2813,
                        2822,
                        2831,
                        2857,
                        2917,
                        2927,
                        2933,
                        2946,
                        3035,
                        3044,
                        3087,
                        3089,
                        3125,
                        3129,
                        3130,
                        3147,
                        3152,
                        3163,
                        3179,
                        3205,
                        3215,
                        3231,
                        3236,
                        3247,
                        3257,
                        3265,
                        3272,
                        3288,
                        3316,
                        3324,
                        3334,
                        3352,
                        3387,
                        3389,
                        3420,
                        3440,
                        3443,
                        3445,
                        3508,
                        3561,
                        3573,
                        3592,
                        3611,
                        3622,
                        3623,
                        3653,
                        3661,
                        3664,
                        3668,
                        3672,
                        3716,
                        3722,
                        3727,
                        3737,
                        3744,
                        3768,
                        3814,
                        3857,
                        3873,
                        3885,
                        3889,
                        3930,
                        3952,
                        4003,
                        4018,
                        4032,
                        4080,
                        4109,
                        4129,
                        4131,
                        4139,
                        4156,
                        4217,
                        4231,
                        4280,
                        4336,
                        4337,
                        4339,
                        4342,
                        4366,
                        4387,
                        4417,
                        4450,
                        4503,
                        4506,
                        4513,
                        4541,
                        4543,
                        4559,
                        4568,
                        4596,
                        4601,
                        4608,
                        4611,
                        4621,
                        4634,
                        4688,
                        4713,
                        4726,
                        4750,
                        4792,
                        4811,
                        4835,
                        4855,
                        4857,
                        4863,
                        4888,
                        4892,
                        4913,
                        4945,
                        4973,
                        5002,
                        5023,
                        5027,
                        5080,
                        5117,
                        5134,
                        5180,
                        5181,
                        5184,
                        5193,
                        5195,
                        5221,
                        5223,
                        5266,
                        5268,
                        5316,
                        5328,
                        5355,
                        5389,
                        5398,
                        5406,
                        5440,
                        5457,
                        5499,
                        5509,
                        5527,
                        5533,
                        5537,
                        5568,
                        5586,
                        5618,
                        5621,
                        5638,
                        5677,
                        5713,
                        5719,
                        5721,
                        5785,
                        5795,
                        5836,
                        5837,
                        5848,
                        5851,
                        5854,
                        5862,
                        5866,
                        5883,
                        5929,
                        5974,
                        6025,
                        6054,
                        6057,
                        6068,
                        6093,
                        6106,
                        6121,
                        6132,
                        6133,
                        6155,
                        6185,
                        6217,
                        6226,
                        6227,
                        6237,
                        6256,
                        6262,
                        6340,
                        6358,
                        6433,
                        6468,
                        6473,
                        6478,
                        6502,
                        6511,
                        6550,
                        6561,
                        6566,
                        6571,
                        6601,
                        6639,
                        6668,
                        6696,
                        6698,
                        6709,
                        6710,
                        6725,
                        6765,
                        6779,
                        6787,
                        6806,
                        6807,
                        6815,
                        6831,
                        6841,
                        6842,
                        6852,
                        6890,
                        6910,
                        6929,
                        6935,
                        6946,
                        6949,
                        6959,
                        6976,
                        6985,
                        6989,
                        7008,
                        7031,
                        7063,
                        7070,
                        7072,
                        7108,
                        7125,
                        7141,
                        7162,
                        7188,
                        7197,
                        7204,
                        7211,
                        7214,
                        7217,
                        7230,
                        7242,
                        7287,
                        7303,
                        7306,
                        7308,
                        7336,
                        7374,
                        7387,
                        7392,
                        7439,
                        7447,
                        7456,
                        7468,
                        7470,
                        7476,
                        7497,
                        7545,
                        7558,
                        7572,
                        7576,
                        7591,
                        7601,
                        7602,
                        7645,
                        7653,
                        7673,
                        7682,
                        7690,
                        7767,
                        7769,
                        7786,
                        7788,
                        7792,
                        7800,
                        7839,
                        7851,
                        7858,
                        7891,
                        7903,
                        7908,
                        7912,
                        7962,
                        7997,
                        8008,
                        8036,
                        8045,
                        8057,
                        8058,
                        8060,
                        8108,
                        8126,
                        8138,
                        8158,
                        8163,
                        8164,
                        8194,
                        8200,
                        8245,
                        8275,
                        8289,
                        8314,
                        8378,
                        8393,
                        8401,
                        8450,
                        8454,
                        8473,
                        8476,
                        8480,
                        8492,
                        8497,
                        8535,
                        8553,
                        8564,
                        8589,
                        8612,
                        8625,
                        8647,
                        8653,
                        8694,
                        8695,
                        8707,
                        8723,
                        8738,
                        8772,
                        8784,
                        8804,
                        8815,
                        8822,
                        8873,
                        8897,
                        8913,
                        8935,
                        8946,
                        8978,
                        8987,
                        8989,
                        9034,
                        9043,
                        9053,
                        9075,
                        9081,
                        9088,
                        9089,
                        9150,
                        9156,
                        9173,
                        9175,
                        9186,
                        9211,
                        9238,
                        9259,
                        9270
                    ],
                    "inconsistent_record_example": "inconsistencies/age/child_MSP_example.csv"
                },
                {
                    "inconsistency_name": "child_PINCP_DECILE",
                    "inconsistency_description": "Children (< 15) don't have personal incomes",
                    "inconsistency_features": [
                        "AGEP",
                        "PINCP_DECILE"
                    ],
                    "inconsistency_violations": 503,
                    "inconsistent_data_indexes": [
                        8,
                        9,
                        32,
                        59,
                        101,
                        103,
                        122,
                        144,
                        187,
                        210,
                        218,
                        230,
                        232,
                        257,
                        262,
                        272,
                        281,
                        333,
                        337,
                        348,
                        349,
                        351,
                        366,
                        397,
                        398,
                        420,
                        447,
                        448,
                        494,
                        534,
                        557,
                        570,
                        592,
                        599,
                        614,
                        627,
                        634,
                        656,
                        725,
                        741,
                        760,
                        764,
                        776,
                        785,
                        797,
                        808,
                        811,
                        832,
                        835,
                        839,
                        849,
                        862,
                        888,
                        928,
                        936,
                        941,
                        950,
                        971,
                        978,
                        999,
                        1041,
                        1054,
                        1063,
                        1065,
                        1098,
                        1099,
                        1142,
                        1143,
                        1164,
                        1190,
                        1216,
                        1223,
                        1225,
                        1242,
                        1253,
                        1267,
                        1298,
                        1302,
                        1308,
                        1345,
                        1347,
                        1373,
                        1380,
                        1388,
                        1406,
                        1408,
                        1424,
                        1467,
                        1486,
                        1512,
                        1569,
                        1595,
                        1606,
                        1624,
                        1626,
                        1664,
                        1691,
                        1702,
                        1708,
                        1712,
                        1735,
                        1738,
                        1767,
                        1784,
                        1805,
                        1831,
                        1860,
                        1869,
                        1887,
                        1894,
                        1912,
                        1914,
                        1924,
                        1931,
                        2002,
                        2027,
                        2071,
                        2077,
                        2119,
                        2149,
                        2152,
                        2160,
                        2179,
                        2187,
                        2246,
                        2255,
                        2257,
                        2258,
                        2264,
                        2278,
                        2341,
                        2350,
                        2357,
                        2362,
                        2367,
                        2382,
                        2503,
                        2505,
                        2507,
                        2530,
                        2546,
                        2565,
                        2568,
                        2577,
                        2630,
                        2633,
                        2652,
                        2653,
                        2668,
                        2693,
                        2704,
                        2733,
                        2755,
                        2798,
                        2806,
                        2812,
                        2813,
                        2822,
                        2831,
                        2857,
                        2917,
                        2927,
                        2933,
                        2946,
                        3035,
                        3044,
                        3087,
                        3089,
                        3125,
                        3129,
                        3130,
                        3147,
                        3152,
                        3163,
                        3179,
                        3205,
                        3215,
                        3231,
                        3236,
                        3247,
                        3257,
                        3265,
                        3272,
                        3288,
                        3316,
                        3324,
                        3334,
                        3352,
                        3387,
                        3389,
                        3420,
                        3440,
                        3443,
                        3445,
                        3508,
                        3561,
                        3573,
                        3592,
                        3611,
                        3622,
                        3623,
                        3653,
                        3661,
                        3664,
                        3668,
                        3672,
                        3716,
                        3722,
                        3727,
                        3737,
                        3744,
                        3768,
                        3814,
                        3857,
                        3873,
                        3885,
                        3889,
                        3930,
                        3952,
                        4003,
                        4018,
                        4027,
                        4032,
                        4080,
                        4090,
                        4109,
                        4129,
                        4131,
                        4139,
                        4156,
                        4217,
                        4231,
                        4280,
                        4336,
                        4337,
                        4339,
                        4342,
                        4366,
                        4387,
                        4417,
                        4450,
                        4503,
                        4506,
                        4513,
                        4541,
                        4543,
                        4559,
                        4568,
                        4596,
                        4601,
                        4608,
                        4611,
                        4621,
                        4634,
                        4688,
                        4713,
                        4726,
                        4750,
                        4792,
                        4811,
                        4835,
                        4855,
                        4857,
                        4863,
                        4888,
                        4892,
                        4913,
                        4945,
                        4973,
                        5002,
                        5023,
                        5027,
                        5080,
                        5117,
                        5134,
                        5180,
                        5181,
                        5184,
                        5193,
                        5195,
                        5221,
                        5223,
                        5266,
                        5268,
                        5316,
                        5328,
                        5355,
                        5389,
                        5398,
                        5406,
                        5440,
                        5457,
                        5499,
                        5509,
                        5533,
                        5537,
                        5568,
                        5586,
                        5618,
                        5621,
                        5638,
                        5677,
                        5713,
                        5721,
                        5756,
                        5785,
                        5795,
                        5836,
                        5837,
                        5848,
                        5851,
                        5854,
                        5862,
                        5866,
                        5883,
                        5929,
                        5974,
                        6025,
                        6054,
                        6057,
                        6068,
                        6093,
                        6106,
                        6121,
                        6132,
                        6133,
                        6155,
                        6185,
                        6226,
                        6227,
                        6237,
                        6256,
                        6262,
                        6319,
                        6340,
                        6358,
                        6433,
                        6468,
                        6473,
                        6478,
                        6502,
                        6511,
                        6550,
                        6561,
                        6566,
                        6571,
                        6601,
                        6639,
                        6668,
                        6696,
                        6698,
                        6709,
                        6710,
                        6725,
                        6765,
                        6779,
                        6787,
                        6806,
                        6807,
                        6815,
                        6831,
                        6841,
                        6842,
                        6852,
                        6890,
                        6910,
                        6929,
                        6935,
                        6946,
                        6949,
                        6959,
                        6976,
                        6985,
                        6989,
                        7008,
                        7031,
                        7063,
                        7070,
                        7072,
                        7108,
                        7125,
                        7141,
                        7162,
                        7188,
                        7197,
                        7204,
                        7211,
                        7214,
                        7217,
                        7230,
                        7242,
                        7287,
                        7303,
                        7306,
                        7336,
                        7374,
                        7387,
                        7392,
                        7424,
                        7439,
                        7447,
                        7456,
                        7468,
                        7476,
                        7497,
                        7545,
                        7558,
                        7572,
                        7576,
                        7591,
                        7601,
                        7602,
                        7645,
                        7653,
                        7673,
                        7682,
                        7690,
                        7767,
                        7769,
                        7786,
                        7788,
                        7792,
                        7800,
                        7839,
                        7851,
                        7858,
                        7891,
                        7903,
                        7908,
                        7912,
                        7962,
                        7997,
                        8008,
                        8036,
                        8045,
                        8057,
                        8058,
                        8060,
                        8108,
                        8126,
                        8138,
                        8158,
                        8163,
                        8164,
                        8194,
                        8200,
                        8245,
                        8275,
                        8289,
                        8314,
                        8378,
                        8393,
                        8401,
                        8450,
                        8454,
                        8473,
                        8476,
                        8480,
                        8492,
                        8497,
                        8535,
                        8553,
                        8564,
                        8589,
                        8612,
                        8625,
                        8647,
                        8653,
                        8694,
                        8695,
                        8707,
                        8723,
                        8738,
                        8772,
                        8784,
                        8804,
                        8815,
                        8822,
                        8854,
                        8873,
                        8897,
                        8913,
                        8935,
                        8946,
                        8978,
                        8987,
                        8989,
                        9034,
                        9043,
                        9053,
                        9075,
                        9081,
                        9088,
                        9089,
                        9150,
                        9156,
                        9173,
                        9175,
                        9186,
                        9211,
                        9238,
                        9259,
                        9270
                    ],
                    "inconsistent_record_example": "inconsistencies/age/child_PINCP_DECILE_example.csv"
                },
                {
                    "inconsistency_name": "adult_N",
                    "inconsistency_description": "Adults ( > 14) must specify values (other than N) for all adult features",
                    "inconsistency_features": [
                        "AGEP",
                        "MSP",
                        "PINCP",
                        "PINCP_DECILE",
                        "EDU",
                        "DPHY",
                        "DREM"
                    ],
                    "inconsistency_violations": 322,
                    "inconsistent_data_indexes": [
                        0,
                        12,
                        22,
                        27,
                        62,
                        77,
                        96,
                        112,
                        200,
                        245,
                        286,
                        302,
                        321,
                        322,
                        350,
                        369,
                        371,
                        462,
                        565,
                        581,
                        601,
                        635,
                        686,
                        707,
                        708,
                        724,
                        751,
                        859,
                        878,
                        882,
                        916,
                        949,
                        958,
                        961,
                        981,
                        984,
                        1043,
                        1067,
                        1206,
                        1247,
                        1337,
                        1349,
                        1369,
                        1421,
                        1470,
                        1483,
                        1491,
                        1515,
                        1547,
                        1568,
                        1573,
                        1611,
                        1625,
                        1638,
                        1657,
                        1658,
                        1703,
                        1720,
                        1816,
                        1818,
                        1819,
                        1858,
                        1866,
                        1897,
                        1909,
                        1910,
                        1959,
                        1967,
                        2042,
                        2053,
                        2058,
                        2070,
                        2091,
                        2219,
                        2285,
                        2304,
                        2379,
                        2398,
                        2422,
                        2432,
                        2436,
                        2450,
                        2455,
                        2457,
                        2486,
                        2529,
                        2540,
                        2611,
                        2654,
                        2734,
                        2767,
                        2774,
                        2778,
                        2784,
                        2814,
                        2817,
                        2864,
                        2884,
                        2907,
                        2915,
                        2926,
                        2939,
                        2952,
                        2967,
                        2989,
                        2990,
                        2994,
                        3045,
                        3048,
                        3136,
                        3206,
                        3213,
                        3218,
                        3221,
                        3262,
                        3271,
                        3312,
                        3385,
                        3401,
                        3464,
                        3467,
                        3474,
                        3479,
                        3535,
                        3657,
                        3675,
                        3680,
                        3711,
                        3738,
                        3740,
                        3759,
                        3767,
                        3818,
                        3823,
                        3825,
                        3944,
                        3950,
                        3956,
                        3960,
                        3978,
                        3985,
                        3993,
                        4105,
                        4123,
                        4146,
                        4152,
                        4182,
                        4196,
                        4279,
                        4283,
                        4403,
                        4414,
                        4443,
                        4447,
                        4457,
                        4492,
                        4500,
                        4522,
                        4539,
                        4566,
                        4711,
                        4716,
                        4759,
                        4787,
                        4839,
                        4851,
                        4871,
                        4962,
                        4980,
                        4986,
                        4996,
                        5033,
                        5100,
                        5172,
                        5178,
                        5191,
                        5251,
                        5258,
                        5265,
                        5296,
                        5318,
                        5324,
                        5333,
                        5349,
                        5362,
                        5366,
                        5374,
                        5383,
                        5411,
                        5429,
                        5462,
                        5467,
                        5479,
                        5495,
                        5535,
                        5572,
                        5593,
                        5647,
                        5708,
                        5711,
                        5718,
                        5739,
                        5741,
                        5768,
                        5772,
                        5777,
                        5800,
                        5808,
                        5860,
                        5872,
                        5896,
                        5924,
                        5927,
                        5953,
                        5964,
                        5984,
                        5987,
                        6001,
                        6039,
                        6077,
                        6186,
                        6275,
                        6285,
                        6305,
                        6334,
                        6389,
                        6398,
                        6408,
                        6410,
                        6414,
                        6462,
                        6475,
                        6559,
                        6562,
                        6569,
                        6595,
                        6605,
                        6638,
                        6666,
                        6716,
                        6720,
                        6726,
                        6759,
                        6760,
                        6804,
                        6869,
                        6927,
                        6994,
                        7025,
                        7027,
                        7081,
                        7082,
                        7104,
                        7133,
                        7172,
                        7174,
                        7187,
                        7224,
                        7231,
                        7260,
                        7266,
                        7267,
                        7292,
                        7364,
                        7375,
                        7397,
                        7411,
                        7419,
                        7504,
                        7505,
                        7556,
                        7559,
                        7617,
                        7620,
                        7649,
                        7655,
                        7671,
                        7747,
                        7761,
                        7803,
                        7815,
                        7829,
                        7843,
                        7881,
                        7919,
                        7959,
                        7968,
                        7999,
                        8046,
                        8097,
                        8124,
                        8325,
                        8355,
                        8367,
                        8388,
                        8423,
                        8445,
                        8546,
                        8563,
                        8582,
                        8591,
                        8631,
                        8759,
                        8768,
                        8863,
                        8881,
                        8892,
                        8907,
                        8940,
                        9011,
                        9054,
                        9078,
                        9103,
                        9104,
                        9111,
                        9140,
                        9167,
                        9190,
                        9193,
                        9218,
                        9242,
                        9247
                    ],
                    "inconsistent_record_example": "inconsistencies/age/adult_N_example.csv"
                },
                {
                    "inconsistency_name": "too_many_children",
                    "inconsistency_description": "Adults needed: Family size must be at least one greater than number of children",
                    "inconsistency_features": [
                        "NOC",
                        "NPF"
                    ],
                    "inconsistency_violations": 436,
                    "inconsistent_data_indexes": [
                        5,
                        29,
                        37,
                        85,
                        101,
                        185,
                        195,
                        197,
                        198,
                        251,
                        252,
                        318,
                        339,
                        355,
                        361,
                        374,
                        379,
                        386,
                        390,
                        396,
                        400,
                        411,
                        455,
                        476,
                        487,
                        489,
                        582,
                        598,
                        607,
                        649,
                        713,
                        715,
                        745,
                        770,
                        776,
                        779,
                        802,
                        810,
                        814,
                        835,
                        859,
                        912,
                        938,
                        993,
                        996,
                        1019,
                        1039,
                        1052,
                        1103,
                        1166,
                        1197,
                        1206,
                        1248,
                        1283,
                        1286,
                        1289,
                        1290,
                        1298,
                        1315,
                        1325,
                        1346,
                        1429,
                        1430,
                        1470,
                        1482,
                        1483,
                        1516,
                        1550,
                        1584,
                        1600,
                        1667,
                        1669,
                        1719,
                        1744,
                        1760,
                        1823,
                        1832,
                        1845,
                        1852,
                        1853,
                        1878,
                        1888,
                        1898,
                        1912,
                        1932,
                        1964,
                        1978,
                        1987,
                        2011,
                        2047,
                        2103,
                        2108,
                        2139,
                        2140,
                        2148,
                        2207,
                        2214,
                        2288,
                        2292,
                        2316,
                        2329,
                        2364,
                        2374,
                        2424,
                        2445,
                        2452,
                        2491,
                        2495,
                        2606,
                        2615,
                        2617,
                        2663,
                        2666,
                        2733,
                        2766,
                        2805,
                        2832,
                        2837,
                        2842,
                        2843,
                        2886,
                        2914,
                        2958,
                        2986,
                        2987,
                        2995,
                        3044,
                        3058,
                        3060,
                        3063,
                        3102,
                        3118,
                        3132,
                        3167,
                        3179,
                        3199,
                        3233,
                        3284,
                        3289,
                        3308,
                        3323,
                        3368,
                        3409,
                        3415,
                        3440,
                        3447,
                        3449,
                        3454,
                        3457,
                        3504,
                        3509,
                        3521,
                        3536,
                        3572,
                        3577,
                        3583,
                        3587,
                        3608,
                        3639,
                        3681,
                        3695,
                        3707,
                        3723,
                        3725,
                        3727,
                        3749,
                        3772,
                        3781,
                        3791,
                        3814,
                        3823,
                        3875,
                        3917,
                        3928,
                        3948,
                        3952,
                        4025,
                        4034,
                        4052,
                        4054,
                        4077,
                        4078,
                        4084,
                        4111,
                        4119,
                        4120,
                        4127,
                        4131,
                        4151,
                        4155,
                        4168,
                        4203,
                        4206,
                        4229,
                        4233,
                        4242,
                        4246,
                        4285,
                        4288,
                        4294,
                        4295,
                        4304,
                        4319,
                        4363,
                        4371,
                        4378,
                        4398,
                        4422,
                        4575,
                        4588,
                        4651,
                        4683,
                        4725,
                        4736,
                        4739,
                        4773,
                        4784,
                        4819,
                        4854,
                        4860,
                        4868,
                        4892,
                        4932,
                        4936,
                        4993,
                        4999,
                        5017,
                        5021,
                        5038,
                        5056,
                        5136,
                        5148,
                        5150,
                        5159,
                        5164,
                        5175,
                        5231,
                        5250,
                        5253,
                        5272,
                        5273,
                        5282,
                        5297,
                        5298,
                        5310,
                        5374,
                        5400,
                        5424,
                        5460,
                        5503,
                        5505,
                        5538,
                        5627,
                        5634,
                        5637,
                        5665,
                        5684,
                        5719,
                        5733,
                        5748,
                        5768,
                        5780,
                        5790,
                        5795,
                        5830,
                        5854,
                        5869,
                        5881,
                        5896,
                        5961,
                        5968,
                        5988,
                        6023,
                        6059,
                        6106,
                        6108,
                        6121,
                        6140,
                        6174,
                        6182,
                        6202,
                        6204,
                        6211,
                        6224,
                        6241,
                        6250,
                        6258,
                        6262,
                        6268,
                        6272,
                        6306,
                        6309,
                        6320,
                        6400,
                        6417,
                        6420,
                        6508,
                        6515,
                        6520,
                        6590,
                        6598,
                        6604,
                        6633,
                        6682,
                        6690,
                        6724,
                        6735,
                        6784,
                        6825,
                        6850,
                        6852,
                        6860,
                        6868,
                        6911,
                        6936,
                        6944,
                        6956,
                        6969,
                        7013,
                        7072,
                        7076,
                        7080,
                        7122,
                        7134,
                        7138,
                        7181,
                        7222,
                        7233,
                        7262,
                        7309,
                        7323,
                        7392,
                        7403,
                        7434,
                        7473,
                        7521,
                        7538,
                        7542,
                        7547,
                        7582,
                        7597,
                        7617,
                        7622,
                        7665,
                        7683,
                        7702,
                        7729,
                        7786,
                        7807,
                        7833,
                        7844,
                        7845,
                        7877,
                        7884,
                        7943,
                        7958,
                        7966,
                        7970,
                        7983,
                        7994,
                        8028,
                        8065,
                        8071,
                        8075,
                        8101,
                        8131,
                        8164,
                        8181,
                        8189,
                        8190,
                        8201,
                        8207,
                        8212,
                        8236,
                        8255,
                        8263,
                        8269,
                        8273,
                        8278,
                        8297,
                        8348,
                        8365,
                        8393,
                        8417,
                        8425,
                        8437,
                        8465,
                        8490,
                        8502,
                        8590,
                        8610,
                        8618,
                        8621,
                        8631,
                        8633,
                        8667,
                        8700,
                        8701,
                        8717,
                        8759,
                        8774,
                        8788,
                        8802,
                        8831,
                        8846,
                        8856,
                        8861,
                        8866,
                        8875,
                        8877,
                        8893,
                        8915,
                        8921,
                        8970,
                        8995,
                        9058,
                        9080,
                        9093,
                        9095,
                        9100,
                        9101,
                        9124,
                        9136,
                        9152,
                        9156,
                        9169,
                        9174,
                        9181,
                        9205,
                        9215,
                        9237,
                        9238,
                        9253,
                        9258,
                        9264,
                        9270
                    ],
                    "inconsistent_record_example": "inconsistencies/work/too_many_children_example.csv"
                }
            ]
        },
        "work": {
            "title": "Work-Based Inconsistencies",
            "description": "These inconsistencies deal with the work and finance features; records with work-based inconsistencies might have high incomes while being in poverty, or have conflicts between their industry code and industry category.",
            "inconsistencies": []
        },
        "housing": {
            "title": "Housing-Based Inconsistencies",
            "description": "These inconsistencies deal with housing and family features; records with household-based inconsistencies might have more children in the house than the total household size, or be residents of group quarters (such as prison inmates) who are listed as owning their residences.",
            "inconsistencies": []
        },
        "summary": [
            {
                "Inconsistency Group": "Age",
                "Number of Records Inconsistent": 833,
                "Percent Records Inconsistent": 9.0
            },
            {
                "Inconsistency Group": "Work",
                "Number of Records Inconsistent": 0,
                "Percent Records Inconsistent": 0.0
            },
            {
                "Inconsistency Group": "Housing",
                "Number of Records Inconsistent": 436,
                "Percent Records Inconsistent": 4.7
            }
        ]
    },
    "unique_exact_matches": {
        "records matched in target data": 96,
        "percent records matched in target data": 1.12,
        "unique target records": 8601,
        "percent unique target records": 92.72
    },
    "apparent_match_distribution": {
        "unique_matched_percents": "apparent_match_distribution/unique_matched_percents.csv",
        "plot": "apparent_match_distribution/apparent_match_distribution.jpg"
    },
    "created_on": "June 19, 2023 20:47:15"
}